LICENSE
yaml_utils/__init__.py
yaml_utils-0.0.4.dist-info/LICENSE
yaml_utils-0.0.4.dist-info/WHEEL
yaml_utils-0.0.4.dist-info/METADATA
yaml_utils-0.0.4.dist-info/RECORD
