Metadata-Version: 2.1
Name: yaml-utils
Version: 0.0.4
Summary: This package will help to read and get parent key & target value for given target key from yaml
Home-page: https://github.com/muralidharan92/yaml-util
License: MIT
Keywords: yaml-utils,yml-utils,yaml,yml,utils
Author: Muralidharan Rajendran
Author-email: muraleedharan005@gmail.com
Requires-Python: >=3.7,<4.0
Classifier: License :: OSI Approved :: MIT License
Classifier: Programming Language :: Python :: 3
Classifier: Programming Language :: Python :: 3.7
Classifier: Programming Language :: Python :: 3.8
Classifier: Programming Language :: Python :: 3.9
Requires-Dist: PyYAML (>=5.4.1,<6.0.0)
Project-URL: Repository, https://github.com/muralidharan92/yaml-util
